lektor_markdown_admonition.py
lektor_markdown_admonition-0.3.1.dist-info/LICENSE
lektor_markdown_admonition-0.3.1.dist-info/METADATA
lektor_markdown_admonition-0.3.1.dist-info/WHEEL
lektor_markdown_admonition-0.3.1.dist-info/entry_points.txt
lektor_markdown_admonition-0.3.1.dist-info/top_level.txt
lektor_markdown_admonition-0.3.1.dist-info/RECORD
