Metadata-Version: 2.1
Name: lektor-markdown-admonition
Version: 0.3.1
Summary: Adds basic admonition tag support to Markdown.
Home-page: http://github.com/lektor/lektor-markdown-admonition
Author: Armin Ronacher
Author-email: armin.ronacher@active-4.com
License: BSD
Keywords: Lektor plugin markdown admonition static-site blog
Platform: UNKNOWN
Classifier: Environment :: Plugins
Classifier: Environment :: Web Environment
Classifier: Framework :: Lektor
Classifier: Intended Audience :: Developers
Classifier: License :: OSI Approved :: BSD License
